[
  {
    "eventID": "evt-001",
    "eventName": "GetCallerIdentity",
    "eventSource": "sts.amazonaws.com",
    "sourceIPAddress": "203.0.113.10",
    "userAgent": "aws-cli/2.x",
    "awsRegion": "us-east-1",
    "userIdentity": {
      "type": "AssumedRole",
      "principalId": "AROAEXAMPLE:session",
      "arn": "arn:aws:sts::111122223333:assumed-role/DevReadOnly/session",
      "sessionContext": {
        "attributes": {
          "mfaAuthenticated": "true"
        }
      }
    },
    "requestParameters": null,
    "errorCode": null
  },
  {
    "eventID": "evt-002",
    "eventName": "CreateAccessKey",
    "eventSource": "iam.amazonaws.com",
    "sourceIPAddress": "185.220.101.7",
    "userAgent": "Boto3/1.34",
    "awsRegion": "us-east-1",
    "userIdentity": {
      "type": "IAMUser",
      "principalId": "AIDAEXAMPLE",
      "arn": "arn:aws:iam::111122223333:user/bad-actor",
      "userName": "bad-actor"
    },
    "requestParameters": {
      "userName": "bad-actor"
    },
    "errorCode": null
  },
  {
    "eventID": "evt-003",
    "eventName": "CreateAccessKey",
    "eventSource": "iam.amazonaws.com",
    "sourceIPAddress": "203.0.113.11",
    "userAgent": "Terraform/1.7",
    "awsRegion": "us-east-1",
    "userIdentity": {
      "type": "IAMUser",
      "principalId": "AIDAEXAMPLE2",
      "arn": "arn:aws:iam::111122223333:user/cicd",
      "userName": "cicd"
    },
    "requestParameters": {
      "userName": "cicd"
    },
    "errorCode": null
  },
  {
    "eventID": "evt-004",
    "eventName": "AssumeRole",
    "eventSource": "sts.amazonaws.com",
    "sourceIPAddress": "45.33.32.156",
    "userAgent": "aws-sdk-go",
    "awsRegion": "us-east-1",
    "userIdentity": {
      "type": "IAMUser",
      "principalId": "AIDAEXAMPLE3",
      "arn": "arn:aws:iam::111122223333:user/developer",
      "userName": "developer"
    },
    "requestParameters": {
      "roleArn": "arn:aws:iam::111122223333:role/OrgAdmin",
      "roleSessionName": "pivot"
    },
    "errorCode": null
  },
  {
    "eventID": "evt-005",
    "eventName": "AssumeRole",
    "eventSource": "sts.amazonaws.com",
    "sourceIPAddress": "203.0.113.10",
    "userAgent": "aws-cli/2.x",
    "awsRegion": "us-east-1",
    "userIdentity": {
      "type": "IAMUser",
      "principalId": "AIDAEXAMPLE4",
      "arn": "arn:aws:iam::111122223333:user/breakglass",
      "userName": "breakglass"
    },
    "requestParameters": {
      "roleArn": "arn:aws:iam::111122223333:role/OrgAdmin",
      "roleSessionName": "maintenance"
    },
    "errorCode": null
  },
  {
    "eventID": "evt-006",
    "eventName": "ConsoleLogin",
    "eventSource": "signin.amazonaws.com",
    "sourceIPAddress": "203.0.113.10",
    "userAgent": "Mozilla/5.0",
    "awsRegion": "us-east-1",
    "userIdentity": {
      "type": "Root",
      "principalId": "111122223333",
      "arn": "arn:aws:iam::111122223333:root",
      "sessionContext": {
        "attributes": {
          "mfaAuthenticated": "false"
        }
      }
    },
    "requestParameters": null,
    "errorCode": null
  },
  {
    "eventID": "evt-007",
    "eventName": "ConsoleLogin",
    "eventSource": "signin.amazonaws.com",
    "sourceIPAddress": "203.0.113.10",
    "userAgent": "Mozilla/5.0",
    "awsRegion": "us-east-1",
    "userIdentity": {
      "type": "Root",
      "principalId": "111122223333",
      "arn": "arn:aws:iam::111122223333:root",
      "sessionContext": {
        "attributes": {
          "mfaAuthenticated": "true"
        }
      }
    },
    "requestParameters": null,
    "errorCode": null
  }
]
